shipstation_api_wrapper/__init__.py
shipstation_api_wrapper/api.py
shipstation_api_wrapper/filter.py
shipstation_api_wrapper/models/order.py
shipstation_api_wrapper/models/product.py
shipstation_api_wrapper-0.1.2.dist-info/WHEEL
shipstation_api_wrapper-0.1.2.dist-info/METADATA
shipstation_api_wrapper-0.1.2.dist-info/RECORD
