Metadata-Version: 2.1
Name: shipstation-api-wrapper
Version: 0.1.2
Summary: Non official Shipstation API wrapper
Author: Vick Mu
Author-email: arbi3400@gmail.com
Requires-Python: >=3.10,<4.0
Classifier: Programming Language :: Python :: 3
Classifier: Programming Language :: Python :: 3.10
Requires-Dist: email-validator (>=2.1.1,<3.0.0)
Requires-Dist: pydantic[email] (>=2.6.3,<3.0.0)
Requires-Dist: requests (>=2.31.0,<3.0.0)
